kscaleos/__init__.py
kscaleos/bindings.cpython-311-darwin.so
kscaleos/py.typed
kscaleos-0.0.1.dist-info/LICENSE
kscaleos-0.0.1.dist-info/METADATA
kscaleos-0.0.1.dist-info/WHEEL
kscaleos-0.0.1.dist-info/top_level.txt
kscaleos-0.0.1.dist-info/RECORD
