Metadata-Version: 2.1
Name: kscaleos
Version: 0.0.1
Summary: The K-Scale Operating System
Home-page: https://github.com/kscalelabs/kscaleos
Author: Benjamin Bolte
Requires-Python: >=3.11
License-File: LICENSE
Provides-Extra: dev
Requires-Dist: black; extra == "dev"
Requires-Dist: darglint; extra == "dev"
Requires-Dist: mypy; extra == "dev"
Requires-Dist: ruff; extra == "dev"
Requires-Dist: pytest; extra == "dev"
